<?xml version="1.0" encoding="utf-8"?>
<odoo>
    <record model="ir.ui.view" id="currency_selector_sale_order_form_view">
        <field name="name">currency.selector.sale.order.form.view</field>
        <field name="model">sale.order</field>
        <field name="inherit_id" ref="sale.view_order_form" />
        <field name="arch" type="xml">
            <xpath expr="//field[@name='pricelist_id']" position="attributes">
                <attribute name="invisible">
                    True
                </attribute>
            </xpath>
            <xpath expr="//field[@name='currency_id']" position="attributes">
                <attribute name="invisible">
                    True
                </attribute>
                <attribute name="readonly">
                    True
                </attribute>
                <attribute name="force_save">
                    True
                </attribute>
            </xpath>
            <xpath expr="//field[@name='currency_id']" position="after">
                <field name="company_id" invisible="True" />
                <field name="locked_currency_id" readonly="state != 'draft'" force_save="1" />
                <field name="safe_margin" readonly="state != 'draft'" />
                <field name="locked_currency_rate"
                    invisible="currency_id == company_id.currency_id"
                    readonly="1"
                    force_save="1" />
            </xpath>
        </field>
    </record>
</odoo>
